guillotina_ldap/__init__.py
guillotina_ldap/interfaces.py
guillotina_ldap/model.py
guillotina_ldap/register_user.py
guillotina_ldap/user.py
guillotina_ldap/utility.py
guillotina_ldap/validator.py
guillotina_ldap/tests/__init__.py
guillotina_ldap/tests/conftest.py
guillotina_ldap/tests/fixtures.py
guillotina_ldap/tests/test_login.py
guillotina_ldap/tests/test_registration.py
guillotina_ldap/tests/test_search.py
guillotina_ldap/tests/test_utility.py
guillotina_ldap-1.0.0a12.dev0.dist-info/METADATA
guillotina_ldap-1.0.0a12.dev0.dist-info/WHEEL
guillotina_ldap-1.0.0a12.dev0.dist-info/entry_points.txt
guillotina_ldap-1.0.0a12.dev0.dist-info/top_level.txt
guillotina_ldap-1.0.0a12.dev0.dist-info/zip-safe
guillotina_ldap-1.0.0a12.dev0.dist-info/RECORD
