Metadata-Version: 2.4
Name: guillotina_ldap
Version: 1.0.0a12.dev0
Summary: guillotina ldap auth support
Home-page: https://pypi.python.org/pypi/guillotina_ldap
Author: Ramon Navarro Bosch
Author-email: ramon@plone.org
License: GPL version 3
Keywords: guillotina async ldap
Classifier: Programming Language :: Python :: 3.7
Classifier: Topic :: Software Development :: Libraries :: Python Modules
Requires-Dist: setuptools
Requires-Dist: guillotina>=6.0
Requires-Dist: bonsai
Requires-Dist: retry
Provides-Extra: test
Requires-Dist: pytest; extra == "test"
Requires-Dist: pytest-docker-fixtures; extra == "test"
Requires-Dist: pytest-aiohttp>=0.3.0; extra == "test"
Dynamic: author
Dynamic: author-email
Dynamic: classifier
Dynamic: description
Dynamic: description-content-type
Dynamic: home-page
Dynamic: keywords
Dynamic: license
Dynamic: provides-extra
Dynamic: requires-dist
Dynamic: summary
